voicecover/__init__.py
voicecover-1.2.0.dist-info/LICENSE
voicecover-1.2.0.dist-info/METADATA
voicecover-1.2.0.dist-info/WHEEL
voicecover-1.2.0.dist-info/top_level.txt
voicecover-1.2.0.dist-info/RECORD
