Metadata-Version: 2.2
Name: voicecover
Version: 1.2.0
License-File: LICENSE
Requires-Dist: requests
Requires-Dist: tensorboardX
Requires-Dist: fairseq
Requires-Dist: faiss-cpu
Requires-Dist: numpy
Requires-Dist: ffmpeg-python
Requires-Dist: praat-parselmouth
Requires-Dist: pyworld
Requires-Dist: torchcrepe
Requires-Dist: edge-tts
Requires-Dist: einops
Requires-Dist: local-attention
Requires-Dist: mega.py
Requires-Dist: wget
Requires-Dist: gdown
Requires-Dist: torch
Requires-Dist: torchaudio
Requires-Dist: torchvision
Dynamic: requires-dist
